circe_ui/__init__.py
circe_ui/__main__.py
circe_ui/config.py
circe_ui/static/Sortable.js
circe_ui/static/app.css
circe_ui/static/app.js
circe_ui/static/dropzone.js
circe_ui/static/index.html
circe_ui_certic-0.0.2.dist-info/entry_points.txt
circe_ui_certic-0.0.2.dist-info/WHEEL
circe_ui_certic-0.0.2.dist-info/METADATA
circe_ui_certic-0.0.2.dist-info/RECORD
